README
msgpack_pypy.py
setup.py
msgpack_pypy.egg-info/PKG-INFO
msgpack_pypy.egg-info/SOURCES.txt
msgpack_pypy.egg-info/dependency_links.txt
msgpack_pypy.egg-info/requires.txt
msgpack_pypy.egg-info/top_level.txt