Metadata-Version: 1.1
Name: msgpack-pypy
Version: 0.0.1
Summary: A msgpack extension with special optimizations for PyPy
Home-page: http://bitbucket.org/antocuni/msgpack-pypy
Author: Antonio Cuni
Author-email: anto.cuni@gmail.com
License: BSD
Keywords: msgpack PyPy
Platform: unix
Platform: linux
Platform: osx
Platform: cygwin
Platform: win32
Classifier: Development Status :: 4 - Beta
Classifier: Environment :: Console
Classifier: License :: OSI Approved :: BSD License
Classifier: Programming Language :: Python
Classifier: Intended Audience :: Developers
Classifier: Operating System :: POSIX
Classifier: Topic :: Utilities
